{
  "$schema": "https://schema.management.azure.com/schemas/2019-04-01/deploymentParameters.json#",
  "contentVersion": "1.0.0.0",
  "parameters": {
    "Prefix": {
      "value": "ACU1"
    },
    "Environment": {
      "value": "G"
    },
    "DeploymentID": {
      "value": "0"
    },
    "Stage": {
      "value": {
        "RoleDefinition": 1,
        "Security": 0,
        "RBAC": 1,
        "PIM": 1,
        "SP": 0
      }
    },
    "Extensions": {
      "value": {}
    },
    "DeploymentInfo": {
      "value": {
        "rolesInfo": [
          {
            "Name": "BenWilkinson",
            "RBAC": [
              {
                "Name": "Key Vault Administrator"
              },
              {
                "Name": "Security Admin"
              },
              {
                "Name": "Reader"
              }
            ]
          },
          {
            "Name": "BenWilkinson-ALT",
            "RBAC": [
              {
                "Name": "Reader"
              }
            ]
          },
          {
            "Name": "SimonAdams",
            "RBAC": [
              {
                "Name": "Reader"
              },
              {
                "Name": "ProviderHub_Contributor"
              }
            ]
          },
          {
            "Name": "AshishChole",
            "RBAC": [
              {
                "Name": "Reader"
              }
            ]
          },
          {
            "Name": "CathyEvans",
            "RBAC": [
              {
                "Name": "Reader"
              }
            ]
          },
          {
            "Name": "SCE_PEF_SEC_DEV",
            "RBAC": [
              {
                "Name": "Azure Service Deploy Release Management Contributor"
              }
            ]
          }
        ],
        "PIMInfo": [
          {
            "Name": "BenWilkinson-ALT",
            "RBAC": [
              {
                "Name": "Owner"
              },
              {
                "Name": "User Access Administrator"
              },
              {
                "Name": "Security Admin"
              }
            ]
          },
          {
            "Name": "SimonAdams-ALT",
            "RBAC": [
              {
                "Name": "Owner"
              }
            ]
          }
        ],
        "SPInfo": [
          {
            "Name": "ADO_{ADOProject}_{RGNAME}",
            "RBAC": [
              {
                "Name": "CSEO DevOps Role"
              }
            ]
          }
        ],
        "SecurityPricingInfo": {
          "Standard": [
            "VirtualMachines",
            "SqlServers",
            "AppServices",
            "StorageAccounts",
            "SqlServerVirtualMachines",
            "KeyVaults",
            "Dns",
            "Arm",
            "Containers",
            "OpenSourceRelationalDatabases",
            "CosmosDbs"
          ],
          "Free": [
            // "KubernetesService",
            // "ContainerRegistry"
          ]
        },
        "RoleDefinitionsInfo": [
          {
            "RoleName": "SF_App_Contributor",
            "description": "Manage Service Fabric Applications",
            "notActions": [],
            "actions": [
              "Microsoft.Resources/subscriptions/resourceGroups/read",
              "Microsoft.Resources/deployments/*",
              "Microsoft.ServiceFabric/clusters/applications/*",
              "Microsoft.ServiceFabric/clusters/applicationTypes/*",
              "Microsoft.ServiceFabric/managedclusters/applications/*",
              "Microsoft.ServiceFabric/managedclusters/applicationTypes/*"
            ]
          },
          {
            "RoleName": "ProviderHub_Contributor",
            "description": "Manage Microsoft ProviderHub",
            "notActions": [],
            "actions": [
              "Microsoft.ProviderHub/*",
              // "Private.SupplyChainDevice/*",    // no provider registered
              "Microsoft.Resources/deployments/*"
            ]
          },
          {
            "RoleName": "DeploymentScripts_Contributor",
            "description": "Allow to deploy DeploymentScripts",
            "notActions": [],
            "actions": [
              "Microsoft.Resources/deploymentScripts/*",
              "Microsoft.ContainerInstance/containerGroups/*"
            ]
          },
          {
            "RoleName": "CloudTest_Contributor",
            "description": "Allow to deploy CloudTest resources e.g. accounts, images and devops pools",
            "notActions": [],
            "actions": [
              "Microsoft.CloudTest/accounts/*",
              "Microsoft.CloudTest/images/*",
              "Microsoft.CloudTest/hostedpools/*"
            ]
          }
        ]
      }
    }
  }
}